autoit_ripper/__init__.py
autoit_ripper/autoit_data.py
autoit_ripper/autoit_unpack.py
autoit_ripper/cli.py
autoit_ripper/decompress.py
autoit_ripper/lame.py
autoit_ripper/mt.py
autoit_ripper/opcodes.py
autoit_ripper/utils.py
autoit_ripper-1.1.1.dist-info/LICENSE
autoit_ripper-1.1.1.dist-info/METADATA
autoit_ripper-1.1.1.dist-info/WHEEL
autoit_ripper-1.1.1.dist-info/entry_points.txt
autoit_ripper-1.1.1.dist-info/top_level.txt
autoit_ripper-1.1.1.dist-info/RECORD
