Metadata-Version: 2.1
Name: autoit-ripper
Version: 1.1.1
Summary: Extract AutoIt scripts embedded in PE binaries
Home-page: https://github.com/nazywam/AutoIt-Ripper
Author: nazywam
Author-email: nazywam@gmail.com
Classifier: Programming Language :: Python :: 3
Classifier: License :: OSI Approved :: MIT License
Classifier: Operating System :: OS Independent
Requires-Python: >=3.6
License-File: LICENSE
Requires-Dist: pefile
